{
  "cards": [
    {
      "slide": 1,
      "title": "2026 개인사업자 주목! 💰 부가세 100% 환급받는 비법 대공개!",
      "visual_desc": "밝고 희망찬 분위기. 사업자등록증, 돈다발, 계산기, 웃는 사업가 이미지 조합. '환급' 키워드를 강조하여 시각적으로 표현. 메인 컬러는 신뢰감을 주는 파란색 계열과 활기찬 노란색 계열을 사용."
    },
    {
      "slide": 2,
      "title": "사업 초기 자금난? 부가세 환급이 핵심!",
      "content": "사업 시작 시 발생하는 초기 투자 비용(임대료, 비품 등)에 포함된 부가세! 돌려받으면 든든한 사업 자금이 됩니다. 일반환급 vs 조기환급 유형도 꼭 확인하세요!",
      "visual_desc": "고민하는 사업가 옆에 돈이 쌓이는 그래프 또는 위로 향하는 화살표. '초기 자금', '현금 흐름' 키워드를 시각화. 안정감을 주는 녹색 계열과 성장 이미지를 강조."
    },
    {
      "slide": 3,
      "title": "놓치면 후회! 부가세 환급 핵심 공제 항목",
      "content": "매입세액 공제는 기본 중의 기본! 사업 관련 모든 지출은 세금계산서, 신용카드 등 '적격증빙' 필수! 의제매입세액, 전자세금계산서 공제도 잊지 마세요.",
      "visual_desc": "체크리스트 아이콘, 돋보기로 영수증/세금계산서를 꼼꼼히 확인하는 손. '적격증빙', '매입세액' 키워드를 강조하는 인포그래픽 요소. 중요한 정보를 강조하는 빨간색 포인트 컬러 사용."
    },
    {
      "slide": 4,
      "title": "2026 홈택스 환급 신청, 이렇게 하세요!",
      "content": "국세청 홈택스 전자신고로 간편하게! 사업용 신용카드 등록은 필수, 모든 증빙은 5년간 꼼꼼히 보관하세요. 복잡하다면 세무 전문가와 상담이 가장 현명합니다.",
      "visual_desc": "홈택스 웹사이트 화면 일부, 컴퓨터/스마트폰 아이콘. '홈택스', '간편 신고', '세무사' 키워드를 시각화. 깔끔하고 직관적인 UI/UX 디자인을 연상시키는 이미지. 신뢰감을 주는 파란색 계열."
    },
    {
      "slide": 5,
      "title": "부가세 환급, 이제 어렵지 않죠?",
      "content": "2026년 개인사업자 부가세 환급, 제대로 알고 돌려받아 사업 성장의 발판으로 삼으세요! 더 자세한 정보는 프로필 링크 블로그에서 확인하세요!",
      "visual_desc": "환급받은 돈으로 활짝 웃는 사업가, 엄지척 아이콘. '성공', '성장' 키워드를 긍정적으로 표현. 팔로우, 프로필 링크 아이콘을 명확하게 배치하여 CTA 유도. 밝고 긍정적인 전체적인 톤앤매너."
    }
  ]
}