{
  "title": "2026 연비좋은차 순위: 하이브리드 vs 가솔린 유지비 비교",
  "meta_description": "2026년, 어떤 차가 가장 연비가 좋을까요? 하이브리드와 가솔린 차량의 2026 연비좋은차 순위를 비교하고, 실제 유지비까지 상세히 분석하여 현명한 선택을 돕습니다. 지금 바로 확인하세요!",
  "slug": "fuel-efficient-car-ranking",
  "tags": [
    "2026 연비좋은차",
    "하이브리드",
    "가솔린",
    "자동차 유지비",
    "연비 순위",
    "친환경차"
  ],
  "json_ld": {
    "@context": "https://schema.org",
    "@type": "BlogPosting",
    "headline": "2026 연비좋은차 순위: 하이브리드 vs 가솔린 유지비 비교",
    "description": "2026년 기준, 연비 좋은 하이브리드 및 가솔린 차량 순위를 비교하고, 실제 유지비를 상세히 분석하여 합리적인 자동차 구매 결정을 돕는 가이드입니다.",
    "author": {
      "@type": "Person",
      "name": "Admin"
    }
  }
}